niimpy/__init__.py
niimpy/_version.py
niimpy/analysis/__init__.py
niimpy/analysis/rhythms.py
niimpy/analysis/social_signature.py
niimpy/config/__init__.py
niimpy/config/config.ini
niimpy/config/config.py
niimpy/exploration/__init__.py
niimpy/exploration/missingness.py
niimpy/exploration/setup_dataframe.py
niimpy/exploration/eda/__init__.py
niimpy/exploration/eda/categorical.py
niimpy/exploration/eda/countplot.py
niimpy/exploration/eda/lineplot.py
niimpy/exploration/eda/missingness.py
niimpy/exploration/eda/punchcard.py
niimpy/preprocessing/__init__.py
niimpy/preprocessing/application.py
niimpy/preprocessing/audio.py
niimpy/preprocessing/battery.py
niimpy/preprocessing/communication.py
niimpy/preprocessing/filter.py
niimpy/preprocessing/location.py
niimpy/preprocessing/sampledata.py
niimpy/preprocessing/screen.py
niimpy/preprocessing/survey.py
niimpy/preprocessing/tracker.py
niimpy/preprocessing/util.py
niimpy/reading/__init__.py
niimpy/reading/csv.py
niimpy/reading/database.py
niimpy/reading/google_takeout.py
niimpy/reading/html_iterator.py
niimpy/reading/mhealth.py
niimpy/reading/sqlite.py
niimpy/reading/util.py
niimpy/sampledata/AwareBattery.csv
niimpy/sampledata/AwareBattery_1month.csv.gz
niimpy/sampledata/AwareScreen_1month.csv.gz
niimpy/sampledata/gps.csv
niimpy/sampledata/mhealth_geolocation.json
niimpy/sampledata/mhealth_heart_rate.json
niimpy/sampledata/mhealth_total_sleep_time.json
niimpy/sampledata/mock_survey.csv
niimpy/sampledata/multiuser.sqlite3
niimpy/sampledata/multiuser_AwareAudio.csv
niimpy/sampledata/multiuser_AwareBattery.csv
niimpy/sampledata/multiuser_AwareCalls.csv
niimpy/sampledata/multiuser_AwareMessages.csv
niimpy/sampledata/multiuser_AwareScreen.csv
niimpy/sampledata/sampledata.py
niimpy/sampledata/singleuser.csv
niimpy/sampledata/singleuser.sqlite3
niimpy/sampledata/singleuser_AwareApplicationNotifications.csv
niimpy/sampledata/sl_activity.csv
niimpy/sampledata/step_summary.csv
niimpy/sampledata/survey_phq9.csv
niimpy-1.3.0.dist-info/LICENSE
niimpy-1.3.0.dist-info/WHEEL
niimpy-1.3.0.dist-info/METADATA
niimpy-1.3.0.dist-info/RECORD
