Metadata-Version: 2.1
Name: niimpy
Version: 1.3.0
Summary: Python module for analysis of behavioral data
Author-email: Digitraceslab <talayeh.aledavood@aalto.fi>
Requires-Python: >=3.8
Requires-Dist: python-dateutil
Requires-Dist: numpy
Requires-Dist: pandas>=2.2
Requires-Dist: matplotlib
Requires-Dist: seaborn
Requires-Dist: plotly
Requires-Dist: scikit-learn
Requires-Dist: coverage
Requires-Dist: geopy
Requires-Dist: kaleido
Requires-Dist: scipy
Requires-Dist: tqdm
Requires-Dist: BeautifulSoup4
Requires-Dist: lxml
Requires-Dist: pyarrow
Requires-Dist: google_takeout_email
Requires-Dist: tqdm
Requires-Dist: tzfpy
Requires-Dist: nbdime ; extra == "docs"
Requires-Dist: numpydoc ; extra == "docs"
Requires-Dist: sphinx_rtd_theme ; extra == "docs"
Requires-Dist: sphinx ; extra == "docs"
Requires-Dist: nbsphinx ; extra == "docs"
Requires-Dist: geopy ; extra == "docs"
Requires-Dist: ipykernel ; extra == "docs"
Requires-Dist: multi_language_sentiment ; extra == "sentiment"
Requires-Dist: pytest ; extra == "test"
Project-URL: Repository, https://github.com/digitraceslab/niimpy
Provides-Extra: docs
Provides-Extra: sentiment
Provides-Extra: test
